biosig.cp313-win_amd64.pyd
libbiosig.a
biosig-3.9.1.dist-info/licenses/LICENSE
biosig-3.9.1.dist-info/METADATA
biosig-3.9.1.dist-info/WHEEL
biosig-3.9.1.dist-info/top_level.txt
biosig-3.9.1.dist-info/RECORD
