Metadata-Version: 2.4
Name: Biosig
Version: 3.9.1
Summary: BioSig - tools for biomedical signal processing
Home-page: https://biosig.sourceforge.io
Author: Alois Schlögl
Author-email: Alois Schlögl <alois.schloegl@gmail.com>
Maintainer-email: Alois Schlögl <alois.schloegl@gmail.com>
License:                     GNU GENERAL PUBLIC LICENSE
Project-URL: Homepage, https://biosig.sourceforge.io
Project-URL: Documentation, https://sourceforge.net/p/biosig/wiki/Home/
Project-URL: Repository, https://git.code.sf.net/p/biosig/code
Project-URL: Changelog, https://pub.ista.ac.at/~schloegl/biosig/RELEASE-NOTES
Keywords: EEG,ECG,EKG,EMG,EOG,Polysomnography,ECoG,biomedical signals,SCP,EDF,GDF,HEKA,CFS,ABF
Classifier: Programming Language :: Python
Classifier: Operating System :: OS Independent
License-File: LICENSE
Requires-Dist: numpy
Dynamic: author
Dynamic: home-page
Dynamic: license-file
